ytpb_mpv/__init__.py
ytpb_mpv/__main__.py
ytpb_mpv/cli.py
ytpb_mpv/listener.py
ytpb_mpv-2024.4.12.dist-info/METADATA
ytpb_mpv-2024.4.12.dist-info/WHEEL
ytpb_mpv-2024.4.12.dist-info/entry_points.txt
ytpb_mpv-2024.4.12.dist-info/licenses/LICENSE
ytpb_mpv-2024.4.12.dist-info/licenses/LICENSE~
ytpb_mpv-2024.4.12.dist-info/RECORD
