Metadata-Version: 2.1
Name: ytpb-mpv
Version: 2024.4.12
Summary: A socket listener to complement mpv-ytpb
Author: Maxim Stolyarchuk
License: MIT License
License-File: LICENSE
License-File: LICENSE~
Keywords: mpv,youtube
Classifier: Development Status :: 4 - Beta
Classifier: Environment :: Console
Classifier: Programming Language :: Python
Classifier: Programming Language :: Python :: 3.11
Classifier: Programming Language :: Python :: 3.12
Requires-Python: >=3.11
Requires-Dist: python-mpv-jsonipc>=1.2.0
Requires-Dist: ytpb>=2024.4.12
